Metadata-Version: 2.1
Name: tatts
Version: 1.2
Summary: UNKNOWN
Home-page: https://github.com/ORI299/ttast
Author: ori299
Author-email: email@example.com
License: MIT
Keywords: tatts translate and tts text to speak
Platform: UNKNOWN
